django_yacon-0.8.0.dist-info/DESCRIPTION.rst
django_yacon-0.8.0.dist-info/METADATA
django_yacon-0.8.0.dist-info/metadata.json
django_yacon-0.8.0.dist-info/RECORD
django_yacon-0.8.0.dist-info/top_level.txt
django_yacon-0.8.0.dist-info/WHEEL
yacon/__init__.py
yacon/admin.py
yacon/conf.py
yacon/context_processors.py
yacon/curators.py
yacon/decorators.py
yacon/definitions.py
yacon/forms.py
yacon/helpers.py
yacon/loaders.py
yacon/sanitizer.py
yacon/tests.py
yacon/urls.py
yacon/utils.py
yacon/examples/__init__.py
yacon/examples/dynamic.py
yacon/management/__init__.py
yacon/management/commands/__init__.py
yacon/management/commands/yacon_add_site.py
yacon/management/commands/yacon_create_defaults.py
yacon/management/commands/yacon_create_test_data.py
yacon/management/commands/yacon_fix_thumbnails.py
yacon/management/commands/yacon_run.py
yacon/models/__init__.py
yacon/models/common.py
yacon/models/content.py
yacon/models/groupsq.py
yacon/models/hierarchy.py
yacon/models/pages.py
yacon/models/site.py
yacon/models/users.py
yacon/pagination/__init__.py
yacon/pagination/middleware.py
yacon/pagination/models.py
yacon/pagination/paginator.py
yacon/pagination/tests.py
yacon/static/yacon/ckeditor/build-config.js
yacon/static/yacon/ckeditor/ckeditor.js
yacon/static/yacon/ckeditor/config.js
yacon/static/yacon/ckeditor/contents.css
yacon/static/yacon/ckeditor/styles.js
yacon/static/yacon/ckeditor/adapters/jquery.js
yacon/static/yacon/ckeditor/lang/af.js
yacon/static/yacon/ckeditor/lang/ar.js
yacon/static/yacon/ckeditor/lang/bg.js
yacon/static/yacon/ckeditor/lang/bn.js
yacon/static/yacon/ckeditor/lang/bs.js
yacon/static/yacon/ckeditor/lang/ca.js
yacon/static/yacon/ckeditor/lang/cs.js
yacon/static/yacon/ckeditor/lang/cy.js
yacon/static/yacon/ckeditor/lang/da.js
yacon/static/yacon/ckeditor/lang/de.js
yacon/static/yacon/ckeditor/lang/el.js
yacon/static/yacon/ckeditor/lang/en-au.js
yacon/static/yacon/ckeditor/lang/en-ca.js
yacon/static/yacon/ckeditor/lang/en-gb.js
yacon/static/yacon/ckeditor/lang/en.js
yacon/static/yacon/ckeditor/lang/eo.js
yacon/static/yacon/ckeditor/lang/es.js
yacon/static/yacon/ckeditor/lang/et.js
yacon/static/yacon/ckeditor/lang/eu.js
