Metadata-Version: 2.0
Name: django-yacon
Version: 0.8.0
Summary: Django based Content Managment building framework
Home-page: https://github.com/cltrudeau/django-yacon
Author: Christopher Trudeau
Author-email: ctrudeau+pypi@arsensa.com
License: MIT
Keywords: django,CMS
Platform: UNKNOWN
Classifier: Development Status :: 4 - Beta
Classifier: Environment :: Web Environment
Classifier: Intended Audience :: Developers
Classifier: License :: OSI Approved :: MIT License
Classifier: Operating System :: OS Independent
Classifier: Programming Language :: Python :: 2
Classifier: Programming Language :: Python :: 2.7
Classifier: Topic :: Software Development :: Libraries :: Application Frameworks
Classifier: Topic :: Software Development :: Libraries :: Python Modules
Requires-Dist: Django (>=1.7)
Requires-Dist: Pillow (>=2.7)
Requires-Dist: bleach (>=1.4)
Requires-Dist: django-treebeard (>=3)
